snapper_systemd_boot/__init__.py
snapper_systemd_boot/cli.py
snapper_systemd_boot/config.py
snapper_systemd_boot/conftest.py
snapper_systemd_boot/context.py
snapper_systemd_boot/manager.py
snapper_systemd_boot/snapper.py
snapper_systemd_boot-0.1.0.dev2.dist-info/DESCRIPTION.rst
snapper_systemd_boot-0.1.0.dev2.dist-info/METADATA
snapper_systemd_boot-0.1.0.dev2.dist-info/RECORD
snapper_systemd_boot-0.1.0.dev2.dist-info/WHEEL
snapper_systemd_boot-0.1.0.dev2.dist-info/entry_points.txt
snapper_systemd_boot-0.1.0.dev2.dist-info/metadata.json
snapper_systemd_boot-0.1.0.dev2.dist-info/top_level.txt
