Metadata-Version: 2.0
Name: snapper-systemd-boot
Version: 0.1.0.dev2
Summary: Generate systemd-boot entries from snapper btrfs snapshots.
Home-page: UNKNOWN
Author: Chris Scutcher
Author-email: chris@scutcher.uk
License: Apache-2.0
Keywords: systemd-boot snapper btrfs
Platform: UNKNOWN
Classifier: Development Status :: 2 - Pre-Alpha
Classifier: License :: OSI Approved :: Apache Software License
Classifier: Environment :: Console
Classifier: Intended Audience :: Developers
Classifier: Natural Language :: English
Classifier: Operating System :: POSIX :: Linux
Classifier: Programming Language :: Python :: 3 :: Only
Classifier: Programming Language :: Python :: 3.6
Classifier: Topic :: System :: Archiving :: Backup
Classifier: Topic :: System :: Systems Administration
Requires-Python: >=3.6
Provides-Extra: dev
Requires-Dist: reprutils
Requires-Dist: argh
Requires-Dist: sh
Provides-Extra: dev
Requires-Dist: pytest; extra == 'dev'
